src/__init__.py
src/main.py
src/utils.py
tests/__init__.py
tests/test_twc.py
twsc-0.9.1.dist-info/LICENSE
twsc-0.9.1.dist-info/METADATA
twsc-0.9.1.dist-info/WHEEL
twsc-0.9.1.dist-info/entry_points.txt
twsc-0.9.1.dist-info/top_level.txt
twsc-0.9.1.dist-info/RECORD
