Metadata-Version: 2.1
Name: twsc
Version: 0.9.1
Summary: A tool to clean trailing whitespace from recently changed lines or an entire codebase.
Home-page: https://github.com/letsgogeeky/twc
Author: Ramy Moussa
Author-email: ramymaster99@gmail.com
Classifier: Programming Language :: Python :: 3
Classifier: License :: OSI Approved :: MIT License
Classifier: Operating System :: OS Independent
Requires-Python: >=3.7
License-File: LICENSE
Requires-Dist: setuptools
